heims/__init__.py
heims-1.0.0.dist-info/METADATA
heims-1.0.0.dist-info/WHEEL
heims-1.0.0.dist-info/top_level.txt
heims-1.0.0.dist-info/RECORD
