Metadata-Version: 2.1
Name: heims
Version: 1.0.0
Summary: 基础后端管理框架
Author-email: Huey <421425339@qq.com>
License: MIT
Project-URL: Homepage, https://github.com/you/my-pkg
Project-URL: Documentation, https://my-pkg.readthedocs.io
Requires-Python: >=3.7.4
Requires-Dist: Django >=2.0.7
Requires-Dist: mysqlclient >=2.1.0
Provides-Extra: dev
Requires-Dist: black ; extra == 'dev'
Requires-Dist: mypy ; extra == 'dev'
Provides-Extra: test
Requires-Dist: pytest >=7.0 ; extra == 'test'
